grave/__init__.py
grave/_layout.py
grave/_nx_pylab.py
grave/grave.py
grave/style.py
grave/tests/__init__.py
grave/tests/conftest.py
grave/tests/test_grave.py
grave/tests/test_style.py
grave-0.0.3.dist-info/METADATA
grave-0.0.3.dist-info/RECORD
grave-0.0.3.dist-info/WHEEL
grave-0.0.3.dist-info/top_level.txt
