Metadata-Version: 2.1
Name: grave
Version: 0.0.3
Summary: Dead simple graph visualization
Home-page: http://github.com/networkx/grave
Author: Grave Developers
Author-email: networkx-discuss@googlegroups.com
License: BSD
Platform: UNKNOWN
